jinja2_async_environment/__init__.py
jinja2_async_environment/bccache.py
jinja2_async_environment/compiler.py
jinja2_async_environment/environment.py
jinja2_async_environment/.skylos/cache.sqlite
jinja2_async_environment/caching/__init__.py
jinja2_async_environment/caching/manager.py
jinja2_async_environment/caching/strategies.py
jinja2_async_environment/caching/typed.py
jinja2_async_environment/caching/unified.py
jinja2_async_environment/compiler_modules/__init__.py
jinja2_async_environment/compiler_modules/cache.py
jinja2_async_environment/compiler_modules/codegen.py
jinja2_async_environment/compiler_modules/dependencies.py
jinja2_async_environment/compiler_modules/frame.py
jinja2_async_environment/compiler_modules/loops.py
jinja2_async_environment/compiler_modules/patterns.py
jinja2_async_environment/loaders/__init__.py
jinja2_async_environment/loaders/base.py
jinja2_async_environment/loaders/choice.py
jinja2_async_environment/loaders/dict.py
jinja2_async_environment/loaders/filesystem.py
jinja2_async_environment/loaders/function.py
jinja2_async_environment/loaders/package.py
jinja2_async_environment/testing/__init__.py
jinja2_async_environment/testing/context.py
jinja2_async_environment/testing/fixtures.py
jinja2_async_environment-0.18.7.dist-info/METADATA
jinja2_async_environment-0.18.7.dist-info/WHEEL
jinja2_async_environment-0.18.7.dist-info/licenses/LICENSE
jinja2_async_environment-0.18.7.dist-info/RECORD
