Metadata-Version: 2.4
Name: jinja2-async-environment
Version: 0.18.7
Summary: Provides asynchronous alternatives to Jinja2's standard template environment and loaders
Author-email: lesleslie <les@wedgwoodwebworks.com>
License: BSD-3-Clause
License-File: LICENSE
Classifier: Development Status :: 4 - Beta
Classifier: Framework :: AsyncIO
Classifier: Framework :: FastAPI
Classifier: License :: OSI Approved :: BSD License
Classifier: Operating System :: OS Independent
Classifier: Programming Language :: Python
Classifier: Programming Language :: Python :: 3 :: Only
Classifier: Programming Language :: Python :: 3.13
Classifier: Topic :: Internet :: WWW/HTTP :: Dynamic Content
Classifier: Typing :: Typed
Requires-Python: >=3.13
Requires-Dist: anyio>=4.11.0
Requires-Dist: jinja2>=3.1.6
Requires-Dist: redis>=7.1.0
